orbitdbapi/__init__.py
orbitdbapi/client.py
orbitdbapi/db.py
orbitdbapi/version.py
orbitdbapi-0.4.1.dev0.dist-info/LICENSE
orbitdbapi-0.4.1.dev0.dist-info/METADATA
orbitdbapi-0.4.1.dev0.dist-info/WHEEL
orbitdbapi-0.4.1.dev0.dist-info/top_level.txt
orbitdbapi-0.4.1.dev0.dist-info/RECORD
