Metadata-Version: 2.1
Name: orbitdbapi
Version: 0.4.1.dev0
Summary: A Python HTTP Orbitdb API Client
Home-page: https://github.com/orbitdb/py-orbit-db-http-client
Author: Phillip Mackintosh
Classifier: Programming Language :: Python :: 3
Classifier: License :: OSI Approved :: MIT License
Classifier: Operating System :: OS Independent
License-File: LICENSE
Requires-Dist: httpx (>=0.7.5)
Requires-Dist: sseclient (==0.0.24)
